Metadata-Version: 2.1
Name: odoo-addon-payment-mode-report-invoice
Version: 16.0.0.0.0
Summary: Adapts payment information by payment mode
Home-page: https://coopdevs.org
Author: Coopdevs Treball SCCL
License: AGPL-3
Platform: UNKNOWN
Classifier: Programming Language :: Python
Classifier: Framework :: Odoo
Classifier: Framework :: Odoo :: 16.0
Classifier: License :: OSI Approved :: GNU Affero General Public License v3
Requires-Python: >=3.10
Requires-Dist: odoo (<16.1dev,>=16.0a)
